geodev/__init__.py
geodev/common.py
geodev/foliumap.py
geodev/geodev.py
geodev-0.1.0.dist-info/licenses/LICENSE
geodev-0.1.0.dist-info/METADATA
geodev-0.1.0.dist-info/WHEEL
geodev-0.1.0.dist-info/entry_points.txt
geodev-0.1.0.dist-info/top_level.txt
geodev-0.1.0.dist-info/RECORD
